python_signal_cli_rest_api/__init__.py
python_signal_cli_rest_api/api/__init__.py
python_signal_cli_rest_api/api/about.py
python_signal_cli_rest_api/api/groups.py
python_signal_cli_rest_api/api/profiles.py
python_signal_cli_rest_api/api/reactions.py
python_signal_cli_rest_api/api/register_verify.py
python_signal_cli_rest_api/api/search.py
python_signal_cli_rest_api/api/send.py
python_signal_cli_rest_api/api/configuration/__init__.py
python_signal_cli_rest_api/dataclasses/__init__.py
python_signal_cli_rest_api/lib/__init__.py
python_signal_cli_rest_api/lib/helper/__init__.py
python_signal_cli_rest_api/lib/jsonrpc/__init__.py
python_signal_cli_rest_api/openapi/assets/swagger/swagger-ui-bundle.min.js
python_signal_cli_rest_api/openapi/assets/swagger/swagger-ui-standalone-preset.min.js
python_signal_cli_rest_api/openapi/assets/swagger/swagger-ui.min.css
python_signal_cli_rest_api/openapi/assets/swagger/swagger.html
python_signal_cli_rest_api/version/__init__.py
python_signal_cli_rest_api-22.10.6.dist-info/LICENSE
python_signal_cli_rest_api-22.10.6.dist-info/METADATA
python_signal_cli_rest_api-22.10.6.dist-info/WHEEL
python_signal_cli_rest_api-22.10.6.dist-info/entry_points.txt
python_signal_cli_rest_api-22.10.6.dist-info/top_level.txt
python_signal_cli_rest_api-22.10.6.dist-info/RECORD
