Metadata-Version: 2.1
Name: python-signal-cli-rest-api
Version: 22.10.6
Author: Stefan Heitmüller
Author-email: stefan.heitmueller@gmx.com
License: MIT
Requires-Python: ~=3.8
License-File: LICENSE
Requires-Dist: sanic (==22.9.0)
Requires-Dist: sanic-ext (==22.9.0)
Requires-Dist: pydantic (==1.10.2)
Requires-Dist: python-magic (==0.4.24)
Requires-Dist: jmespath (==1.0.1)
Requires-Dist: pyyaml (==6.0)
